todsl/__init__.py
todsl/__main__.py
todsl-0.0.1.dist-info/LICENSE
todsl-0.0.1.dist-info/METADATA
todsl-0.0.1.dist-info/WHEEL
todsl-0.0.1.dist-info/entry_points.txt
todsl-0.0.1.dist-info/top_level.txt
todsl-0.0.1.dist-info/RECORD
