Metadata-Version: 2.1
Name: todsl
Version: 0.0.1
Summary: A JDSL-like disasterpiece, but with Git and TOML.
Author-email: hexaheximal <hexaheximal@proton.me>
Maintainer-email: hexaheximal <hexaheximal@proton.me>
License: Copyright (C) 2024 by hexaheximal <hexaheximal@proton.me>
Project-URL: Repository, https://codeberg.org/todsl/todsl.git
Keywords: TOML,DSL,JDSL,TomIsAGenius
Classifier: Development Status :: 4 - Beta
Classifier: Programming Language :: Python
Requires-Python: >=3.11
License-File: LICENSE
Requires-Dist: GitPython >=3.1.43
